leaseweb_api/__init__.py
leaseweb_api/auth_provider.py
leaseweb_api/dedicated_servers.py
leaseweb_api/dedicated_services.py
leaseweb_api/py.typed
leaseweb_api/config/__init__.py
leaseweb_api/config/config.py
leaseweb_api/helper/__init__.py
leaseweb_api/helper/helpers.py
leaseweb_api/types/contract.py
leaseweb_api/types/credentials.py
leaseweb_api/types/dedicated_server.py
leaseweb_api/types/enums.py
leaseweb_api/types/error.py
leaseweb_api/types/hardware.py
leaseweb_api/types/jobs.py
leaseweb_api/types/metrics.py
leaseweb_api/types/network.py
leaseweb_api/types/notification.py
leaseweb_api/types/parameters.py
leaseweb_api/types/rack.py
leaseweb_api/types/software.py
leaseweb_api-0.1.1.dist-info/METADATA
leaseweb_api-0.1.1.dist-info/WHEEL
leaseweb_api-0.1.1.dist-info/licenses/LICENSE.md
leaseweb_api-0.1.1.dist-info/RECORD
