Metadata-Version: 2.4
Name: leaseweb-api
Version: 0.1.1
Summary: Leaseweb API Wrapper
Project-URL: Homepage, https://github.com/Sidelane/leaseweb_api_python
Author-email: Andreas Pelger <a.pelger@de.leaseweb.com>
License-Expression: MIT
License-File: LICENSE.md
Requires-Python: >3.11
Requires-Dist: pydantic>=2.10.6
Requires-Dist: requests>=2.32.3
